Metadata-Version: 1.1
Name: pyIOSXR
Version: 0.12
Summary: Python API to interact with network devices running IOS-XR
Home-page: https://github.com/fooelisa/pyiosxr/
Author: Elisa Jasinska
Author-email: elisa@bigwaveit.org
License: UNKNOWN
Download-URL: https://github.com/fooelisa/pyiosxr/tarball/0.12
Keywords: IOS-XR,IOSXR,Cisco,networking
Platform: UNKNOWN
